fortesfit/.gitignore
fortesfit/FortesFit_Filters.py
fortesfit/FortesFit_Fitting.py
fortesfit/FortesFit_Init.py
fortesfit/FortesFit_ModelManagement.py
fortesfit/FortesFit_Parsers.py
fortesfit/FortesFit_Plots.py
fortesfit/FortesFit_Preparation.py
fortesfit/FortesFit_Settings.py
fortesfit/FortesFit_dev.py
fortesfit/FortesFit_emcee.py
fortesfit/FortesFit_installation_test.py
fortesfit/FortesFit_multinest.py
fortesfit/__init__.py
fortesfit/test_model.py
fortesfit-2.0.0.dist-info/METADATA
fortesfit-2.0.0.dist-info/WHEEL
fortesfit-2.0.0.dist-info/licenses/LICENSE
fortesfit-2.0.0.dist-info/RECORD
