Metadata-Version: 2.4
Name: fortesfit
Version: 2.0.0
Summary: Flexible SED fitting for astrophysics
Project-URL: Homepage, http://github.com/vikalibrate/FortesFit
Author-email: David Rosario <david.rosario@ncl.ac.uk>, Devang Liya <d.h.liya2@newcastle.ac.uk>
License-Expression: MIT
License-File: LICENSE
Keywords: SED,astrophysics,bayesian,fitting,multiwavelength
Classifier: Intended Audience :: Science/Research
Classifier: Programming Language :: Python :: 3
Classifier: Topic :: Scientific/Engineering :: Astronomy
Requires-Python: >=3.9
Requires-Dist: astropy
Requires-Dist: corner
Requires-Dist: emcee
Requires-Dist: h5py
Requires-Dist: matplotlib
Requires-Dist: numpy>=1.2
Requires-Dist: scipy<=1.13
Requires-Dist: tqdm
